{
  "project_info": {
    "project_number": "384655473775",
    "firebase_url": "https://stageproject-e1442.firebaseio.com",
    "project_id": "stageproject-e1442",
    "storage_bucket": "stageproject-e1442.appspot.com"
  },
  "client": [
    {
      "client_info": {
        "mobilesdk_app_id": "1:384655473775:android:b2487e1c903676e247a19a",
        "android_client_info": {
          "package_name": "com.thainareis.stageproject"
        }
      },
      "oauth_client": [
        {
          "client_id": "384655473775-is2lmvj90diqfcr8qb3iouh5rd3dkjun.apps.googleusercontent.com",
          "client_type": 3
        }
      ],
      "api_key": [
        {
          "current_key": "AIzaSyCeXM1moHcZCKnqSunKv7YBG8QRgmM4PhQ"
        }
      ],
      "services": {
        "appinvite_service": {
          "other_platform_oauth_client": [
            {
              "client_id": "384655473775-is2lmvj90diqfcr8qb3iouh5rd3dkjun.apps.googleusercontent.com",
              "client_type": 3
            }
          ]
        }
      }
    }
  ],
  "configuration_version": "1"
}